{"cameraMode":{"drawMode":0,"name":"Shaded","section":"Shading Mode"},"sceneLighting":true,"audioPlay":false,"sceneViewState":{"m_AlwaysRefresh":false,"showFog":true,"showSkybox":true,"showFlares":true,"showImageEffects":true,"showParticleSystems":true,"showVisualEffectGraphs":true,"m_FxEnabled":true},"in2DMode":false,"pivot":{"x":10.741057395935059,"y":5.599035263061523,"z":-34.30293655395508},"rotation":{"x":0.10954876989126206,"y":0.025654245167970659,"z":-0.0028301868587732317,"w":0.9936229586601257},"size":10.0,"orthographic":false}